foxyy/__init__.py
foxyy/imports.py
foxyy/main.py
foxyy-0.3.0.dist-info/METADATA
foxyy-0.3.0.dist-info/WHEEL
foxyy-0.3.0.dist-info/entry_points.txt
foxyy-0.3.0.dist-info/RECORD
