Metadata-Version: 2.1
Name: foxyy
Version: 0.3.0
Summary: 
License: MIT
Author: Yoav Kleinberger
Author-email: haarcuba@gmail.com
Requires-Python: >=3.12,<4.0
Classifier: License :: OSI Approved :: MIT License
Classifier: Programming Language :: Python :: 3
Classifier: Programming Language :: Python :: 3.12
Requires-Dist: click (>=8.1.7,<9.0.0)
